LICENSE
MANIFEST.in
README.rst
metadata.py
setup.py
django_redirects_hvad.egg-info/PKG-INFO
django_redirects_hvad.egg-info/SOURCES.txt
django_redirects_hvad.egg-info/dependency_links.txt
django_redirects_hvad.egg-info/not-zip-safe
django_redirects_hvad.egg-info/requires.txt
django_redirects_hvad.egg-info/top_level.txt
redirects_hvad/__init__.py
redirects_hvad/admin.py
redirects_hvad/middleware.py
redirects_hvad/models.py
redirects_hvad/locale/ar/LC_MESSAGES/django.mo
redirects_hvad/locale/ar/LC_MESSAGES/django.po
redirects_hvad/locale/az/LC_MESSAGES/django.mo
redirects_hvad/locale/az/LC_MESSAGES/django.po
redirects_hvad/locale/bg/LC_MESSAGES/django.mo
redirects_hvad/locale/bg/LC_MESSAGES/django.po
redirects_hvad/locale/bn/LC_MESSAGES/django.mo
redirects_hvad/locale/bn/LC_MESSAGES/django.po
redirects_hvad/locale/bs/LC_MESSAGES/django.mo
redirects_hvad/locale/bs/LC_MESSAGES/django.po
redirects_hvad/locale/ca/LC_MESSAGES/django.mo
redirects_hvad/locale/ca/LC_MESSAGES/django.po
redirects_hvad/locale/cs/LC_MESSAGES/django.mo
redirects_hvad/locale/cs/LC_MESSAGES/django.po
redirects_hvad/locale/cy/LC_MESSAGES/django.mo
redirects_hvad/locale/cy/LC_MESSAGES/django.po
redirects_hvad/locale/da/LC_MESSAGES/django.mo
redirects_hvad/locale/da/LC_MESSAGES/django.po
redirects_hvad/locale/de/LC_MESSAGES/django.mo
redirects_hvad/locale/de/LC_MESSAGES/django.po
redirects_hvad/locale/el/LC_MESSAGES/django.mo
redirects_hvad/locale/el/LC_MESSAGES/django.po
redirects_hvad/locale/en/LC_MESSAGES/django.mo
redirects_hvad/locale/en/LC_MESSAGES/django.po
redirects_hvad/locale/en_GB/LC_MESSAGES/django.mo
redirects_hvad/locale/en_GB/LC_MESSAGES/django.po
redirects_hvad/locale/eo/LC_MESSAGES/django.mo
redirects_hvad/locale/eo/LC_MESSAGES/django.po
redirects_hvad/locale/es/LC_MESSAGES/django.mo
redirects_hvad/locale/es/LC_MESSAGES/django.po
redirects_hvad/locale/es_AR/LC_MESSAGES/django.mo
redirects_hvad/locale/es_AR/LC_MESSAGES/django.po
redirects_hvad/locale/es_MX/LC_MESSAGES/django.mo
redirects_hvad/locale/es_MX/LC_MESSAGES/django.po
redirects_hvad/locale/et/LC_MESSAGES/django.mo
redirects_hvad/locale/et/LC_MESSAGES/django.po
redirects_hvad/locale/eu/LC_MESSAGES/django.mo
redirects_hvad/locale/eu/LC_MESSAGES/django.po
