Metadata-Version: 1.1
Name: django-redirects-hvad
Version: 1.1
Summary: A modified version of django.contrib.redirects with multilingual target URLs
Home-page: http://github.com/piquadrat/django-redirects-hvad
Author: Benjamin Wohlwend
Author-email: piquadrat@gmail.com
License: BSD
Platform: OS Independent
Classifier: Development Status :: 4 - Beta
Classifier: Framework :: Django
Classifier: Intended Audience :: Developers
Classifier: License :: OSI Approved :: BSD License
Classifier: Operating System :: OS Independent
Classifier: Programming Language :: Python
Classifier: Topic :: Internet :: WWW/HTTP
